generic_permissions/__init__.py
generic_permissions/apps.py
generic_permissions/config.py
generic_permissions/models.py
generic_permissions/permissions.py
generic_permissions/serializers.py
generic_permissions/validation.py
generic_permissions/views.py
generic_permissions/visibilities.py
django_generic_api_permissions-3.0.0.dist-info/METADATA
django_generic_api_permissions-3.0.0.dist-info/WHEEL
django_generic_api_permissions-3.0.0.dist-info/licenses/LICENSE
django_generic_api_permissions-3.0.0.dist-info/RECORD
