Metadata-Version: 2.4
Name: django-generic-api-permissions
Version: 3.0.0
Summary: Generic API permissions and visibilities for Django
License-File: LICENSE
Author: Adfinis
Author-email: info@adfinis.com
Requires-Python: >=3.12,<4
Classifier: Development Status :: 4 - Beta
Classifier: Environment :: Web Environment
Classifier: Framework :: Django
Classifier: Framework :: Django :: 3.2
Classifier: Framework :: Django :: 4.2
Classifier: Intended Audience :: Developers
Classifier: License :: OSI Approved :: GNU Lesser General Public License v3 or later (LGPLv3+)
Classifier: Operating System :: OS Independent
Classifier: Programming Language :: Python :: 3
Classifier: Programming Language :: Python :: 3.12
Classifier: Programming Language :: Python :: 3.13
Classifier: Programming Language :: Python :: 3.14
Requires-Dist: django (>=3.2)
Requires-Dist: djangorestframework (>=3.14,<4.0)
Project-URL: Repository, https://github.com/adfinis/django-generic-api-permissions
